zensols/showfile/__init__.py
zensols/showfile/app.py
zensols/showfile/browser.py
zensols/showfile/cli.py
zensols/showfile/darwin.py
zensols/showfile/default.py
zensols/showfile/domain.py
zensols/showfile/resources/app.conf
zensols/showfile/resources/obj.conf
zensols/showfile/resources/show-preview.scpt
zensols/showfile/resources/show-safari-multi.scpt
zensols/showfile/resources/show-safari.scpt
zensols.showfile-0.3.0.dist-info/METADATA
zensols.showfile-0.3.0.dist-info/WHEEL
zensols.showfile-0.3.0.dist-info/entry_points.txt
zensols.showfile-0.3.0.dist-info/top_level.txt
zensols.showfile-0.3.0.dist-info/RECORD
