Metadata-Version: 2.1
Name: zensols.showfile
Version: 0.3.0
Summary: Invoke macOS applications to view files
Home-page: https://github.com/plandes/showfile
Download-URL: https://github.com/plandes/showfile/releases/download/v0.3.0/zensols.showfile-0.3.0-py3-none-any.whl
Author: Paul Landes
Author-email: landes@mailc.net
Keywords: tooling
Requires-Dist: screeninfo (~=0.8)
Requires-Dist: zensols.util (~=1.13.0)
